glssm-0.1.dist-info/METADATA
glssm-0.1.dist-info/RECORD
glssm-0.1.dist-info/WHEEL
glssm-0.1.dist-info/top_level.txt
src/__init__.py
src/dlm.cpython-36m-darwin.so
src/ghmm.cpython-36m-darwin.so
